GeoLiberator/__init__.py
GeoLiberator/geoliberator.py
GeoLiberator/gl_beta_test.py
GeoLiberator/sample.py
GeoLiberator-0.3.1.dist-info/LICENSE
GeoLiberator-0.3.1.dist-info/METADATA
GeoLiberator-0.3.1.dist-info/WHEEL
GeoLiberator-0.3.1.dist-info/top_level.txt
GeoLiberator-0.3.1.dist-info/RECORD
