Metadata-Version: 2.1
Name: GeoLiberator
Version: 0.3.1
Summary: A small module that cleans, parses and standardizes addresses
Home-page: https://github.com/jakeee51/GeoLiberator
Author: David J. Morfe
Author-email: jakemorfe@gmail.com
License: MIT
Platform: UNKNOWN
Classifier: Programming Language :: Python :: 3
Classifier: License :: OSI Approved :: MIT License
Classifier: Operating System :: OS Independent
